p1_influx_db/__init__.py
p1_influx_db/__main__.py
p1_influx_db/dsmr_parse.py
p1_influx_db/example_config.toml
p1_influx_db/http_to_influxdb/__init__.py
p1_influx_db/http_to_influxdb/sender.py
p1_influx_db/httpmain.py
p1_influx_db/mqtt/__init__.py
p1_influx_db/mqtt/client.py
p1_influx_db/mqtt/message_store.py
p1_influx_db/mqtt/utils.py
p1_influx_db/mqttmain.py
p1_influx_db-2.5.9.dist-info/LICENSE
p1_influx_db-2.5.9.dist-info/METADATA
p1_influx_db-2.5.9.dist-info/WHEEL
p1_influx_db-2.5.9.dist-info/RECORD
