Metadata-Version: 2.3
Name: p1-influx-db
Version: 2.5.9
Summary: Parsing P1 serial to Influx DB
Author: Yorick Fredrix
Author-email: yorick.fredrix@outlook.com
Requires-Python: >=3.9,<4.0
Classifier: Programming Language :: Python :: 3
Classifier: Programming Language :: Python :: 3.9
Classifier: Programming Language :: Python :: 3.10
Classifier: Programming Language :: Python :: 3.11
Classifier: Programming Language :: Python :: 3.12
Classifier: Programming Language :: Python :: 3.13
Provides-Extra: influxdb
Provides-Extra: mqtt
Provides-Extra: publishmethods
Requires-Dist: dsmr-parser (>=1.3.1,<2.0.0)
Requires-Dist: influxdb-client[async] (>=1.39.0,<2.0.0) ; extra == "influxdb" or extra == "publishmethods"
Requires-Dist: loguru (>=0.7.2,<0.8.0)
Requires-Dist: paho-mqtt (>=2.1.0,<3.0.0) ; extra == "mqtt" or extra == "publishmethods"
Requires-Dist: pydantic (>=2.8.2,<3.0.0)
Requires-Dist: toml (>=0.10.2,<0.11.0)
